{
  "professor": {
    "name": "楊鎮華 教授",
    "image": "assets/images/team/jhyang.jpg",
    "titles": [
      { "icon": "fas fa-user-tie", "text": "國立中央大學 資訊工程學系 講座教授 (2018~)" },
      { "icon": "fas fa-user-tie", "text": "國立中央大學 研發長 兼 高教深耕執行長 (2021~)" },
      { "icon": "fas fa-user-tie", "text": "前教育部資訊及科技教育司司長 (2013~2014)" },
      { "icon": "fas fa-user-tie", "text": "前國科會資訊教育學門召集人 (2012)" }
    ],
    "honors": [
      { "icon": "fas fa-award", "text": "國科會 傑出研究獎 (2010, 2017)" },
      { "icon": "fas fa-award", "text": "教育部 教育專業獎章 (2015)" },
      { "icon": "fas fa-award", "text": "中國電機工程學會會士 (2024)" }
    ],
    "email": "jhyang@csie.ncu.edu.tw",
    "office": "工程五館 E5-A408",
    "ext": "03-4227151-35308"
  },
  "postdocs": [
    {
      "name": "黃鈺晴(Anna)",
      "image": "assets/images/team/黃鈺晴.jpg",
      "email": "anna.yuqing@gmail.com",
      "office": "工程五館 E5-B320",
      "ext": "35356"
    }
  ],
  "assistants": [
    {
      "name": "李鴻怡(Joyce)",
      "image": "assets/images/team/鴻怡.jpg",
      "email": "leehy@ncu.edu.tw",
      "office": "工程五館 E5-B320",
      "ext": "35353"
    },
    {
      "name": "曾昱瑋",
      "image": "assets/images/team/昱瑋.jpg",
      "email": "tseng19831012@gmail.com",
      "office": "工程五館 E5-B320",
      "ext": "35353"
    },
    {
      "name": "許林慶",
      "image": "assets/images/team/林慶.jpg",
      "email": "csiericky09242025@gmail.com",
      "office": "工程五館 E5-B320",
      "ext": "35353"
    }
  ],
  "phd_students": [
    {
      "name": "林建昌",
      "image": "assets/images/team/cc.jpg",
      "email": "cclin3123@gmail.com",
      "office": "工程五館 E5-B321-1",
      "ext": "35356"
    },
    {
      "name": "蔡惠淳",
      "image": "assets/images/team/惠淳.jpg",
      "email": "yvonne12629@gmail.com",
      "office": "工程五館 E5-B321-1",
      "ext": "35356"
    },
    {
      "name": "梁豪友",
      "image": "assets/images/team/梁豪友.jpg",
      "email": "s102598055@gmail.com",
      "office": "工程五館 E5-B321-1",
      "ext": "35356"
    }
  ],
  "master_students": {
    "second_year": [
      {
        "name": "劉品媛",
        "image": "assets/images/team/品媛.jpg",
        "email": "pinyuanliu9@gmail.com",
        "office": "工程五館 E5-B321-1",
        "ext": "335353"
      },
      {
        "name": "游政叡",
        "image": "assets/images/team/政叡.jpg",
        "email": "r910529@gmail.com",
        "office": "工程五館 E5-B321-1",
        "ext": "35353"
      },
      {
        "name": "王裕傑",
        "image": "assets/images/team/裕傑.jpg",
        "email": "jayyu1w@gmail.com",
        "office": "工程五館 E5-B321-1",
        "ext": "35353"
      },
      {
        "name": "陳玟樺",
        "image": "assets/images/team/玟樺.jpg",
        "email": "nicole6328@gmail.com",
        "office": "工程五館 E5-B321-1",
        "ext": "35353"
      },
      {
        "name": "郭曜誠",
        "image": "assets/images/team/曜誠.jpg",
        "email": "kuo901105aa@gmail.com",
        "office": "工程五館 E5-B321-1",
        "ext": "35353"
      },
      {
        "name": "陳淳瑜",
        "image": "assets/images/team/淳瑜.jpg",
        "email": "monicachen0331@gmail.com",
        "office": "工程五館 E5-B321-1",
        "ext": "35353"
      },
      {
        "name": "劉彥汝",
        "image": "assets/images/team/彥汝.jpg",
        "email": "a113527006@g.ncu.edu.tw",
        "office": "工程五館 E5-B321-1",
        "ext": "35353"
      }
    ],
    "first_year": [
      {
        "name": "張詩曼",
        "image": "assets/images/team/詩曼.jpg",
        "email": "shihman2003@gmail.com",
        "office": "工程五館 E5-B321-1",
        "ext": "35353"
      },
      {
        "name": "鍾昀潔",
        "image": "assets/images/team/鍾昀潔.jpg",
        "email": "yuunjiee313@gmail.com",
        "office": "工程五館 E5-B321-1",
        "ext": "35353"
      },
      {
        "name": "陳彥璋",
        "image": "assets/images/team/陳彥璋.jpg",
        "email": "yenchangchen.ncu@gmail.com",
        "office": "工程五館 E5-B321-1",
        "ext": "35353"
      },
      {
        "name": "譚聲全",
        "image": "assets/images/team/譚聲全.jpg",
        "email": "sheng.c.tan@gmail.com",
        "office": "工程五館 E5-B321-1",
        "ext": "35353"
      },
      {
        "name": "呂訢誠",
        "image": "assets/images/team/訢誠.jpg",
        "email": "xinchenglu10@gmail.com",
        "office": "工程五館 E5-B321-1",
        "ext": "35353"
      },
      {
        "name": "黃子瑄",
        "image": "assets/images/team/黃子瑄.jpg",
        "email": "tzuhsuan5684@gmail.com",
        "office": "工程五館 E5-B321-1",
        "ext": "35353"
      },
      {
        "name": "張愷恩",
        "image": "assets/images/team/張愷恩.png",
        "email": "ken.chang.cs@gmail.com",
        "office": "工程五館 E5-B321-1",
        "ext": "35353"
      },
      {
        "name": "黃致穎",
        "image": "assets/images/team/黃致穎.jpg",
        "email": "chihyinghuang23@gmail.com",
        "office": "工程五館 E5-B321-1",
        "ext": "35353"
      }
    ],
    "zero_year": []
  },
  "alumni": [
    {
      "name": "陳大明",
      "grad_year": 2022,
      "image": "assets/images/team/placeholder.png",
      "company": "Google",
      "title": "軟體工程師"
    },
    {
      "name": "林小美",
      "grad_year": 2021,
      "image": "assets/images/team/placeholder.png",
      "company": "台灣積體電路製造",
      "title": "資料科學家"
    },
    {
      "name": "張三",
      "grad_year": 2023,
      "image": "assets/images/team/placeholder.png",
      "company": "聯發科技",
      "title": "AI 工程師"
    }
  ]
}
